nero_dsdn
