Metadata-Version: 1.0
Name: nero-dsdn
Version: 0.2
Summary: Gaussian distributions
Home-page: UNKNOWN
Author: NA Jackson
Author-email: njackson.gis@gmail.com
License: UNKNOWN
Platform: UNKNOWN
